pyopenadr/__init__.py
pyopenadr-0.5.30.dist-info/METADATA
pyopenadr-0.5.30.dist-info/WHEEL
pyopenadr-0.5.30.dist-info/top_level.txt
pyopenadr-0.5.30.dist-info/RECORD
