Metadata-Version: 2.1
Name: pyopenadr
Version: 0.5.30
Summary: Python3 library for building OpenADR Clients (VENs) and Servers (VTNs). Renamed to OpenLEADR.
Home-page: https://openleadr.org
License: UNKNOWN
Platform: UNKNOWN
Requires-Dist: openleadr (==0.5.30)
